pycgi/__init__.py
pycgi/cgi.py
pycgitb/__init__.py
pycgitb/cgitb.py
libcgi-0.1.2.2.dist-info/METADATA
libcgi-0.1.2.2.dist-info/WHEEL
libcgi-0.1.2.2.dist-info/top_level.txt
libcgi-0.1.2.2.dist-info/RECORD
