Metadata-Version: 2.4
Name: libcgi
Version: 0.1.2.2
Summary: 軽量CGIモジュール
Author: PEN
Project-URL: Homepage, https://github.com/BX293APEN/Python-CGI
Project-URL: Source, https://github.com/BX293APEN/Python-CGI/tree/main/module
Project-URL: Issues, https://github.com/BX293APEN/Python-CGI/issues
Requires-Python: >=3.12
